{"firstName":"Sandro","lastName":"Meira Ricci","id":"o41868","totalStat":{"offSide":17,"yellowCard":8,"redCard":1,"firstHalfExtraTime":8,"secondHalfExtraTime":13},"individualGameStat":[{"offSide":3,"yellowCard":5,"redCard":1,"firstHalfExtraTime":4,"secondHalfExtraTime":4,"IDGame":"f731776"},{"offSide":6,"yellowCard":1,"redCard":0,"firstHalfExtraTime":2,"secondHalfExtraTime":5,"IDGame":"f731795"},{"offSide":8,"yellowCard":2,"redCard":0,"firstHalfExtraTime":2,"secondHalfExtraTime":4,"IDGame":"f731820"}]}