[{"dateTime":"2014-06-19T21:52:30-04:00","formatedDateTime":"2014-06-19 21:52:30","comment":"Match ends, Uruguay 2, England 1.","period":14,"minute":95,"second":0,"sortKey":"2014-06-19 21:52:30","twitterImage":"","twitterHandle":"","twitterURL":"","twitterMediaURL":"","language":""},{"dateTime":"2014-06-19T21:52:14-04:00","formatedDateTime":"2014-06-19 21:52:14","comment":"Second Half ends, Uruguay 2, England 1.","period":2,"minute":95,"second":4,"sortKey":"2014-06-19 21:52:14","twitterImage":"","twitterHandle":"","twitterURL":"","twitterMediaURL":"","language":""},{"dateTime":"2014-06-20T03:09:10-04:00","formatedDateTime":"2014-06-20 03:09:10","comment":"Attempt missed. Phil Jagielka (England) header from the centre of the box misses to the left. Assisted by Wayne Rooney with a cross following a corner.","period":2,"minute":94,"second":24,"sortKey":"2014-06-20 03:09:10","twitterImage":"","twitterHandle":"","twitterURL":"","twitterMediaURL":"","language":""},{"dateTime":"2014-06-20T03:08:41-04:00","formatedDateTime":"2014-06-20 03:08:41","comment":"Corner,  England. Conceded by Cristian Rodríguez.","period":2,"minute":94,"second":7,"sortKey":"2014-06-20 03:08:41","twitterImage":"","twitterHandle":"","twitterURL":"","twitterMediaURL":"","language":""},{"dateTime":"2014-06-19T21:49:25-04:00","formatedDateTime":"2014-06-19 21:49:25","comment":"Attempt missed. Steven Gerrard (England) right footed shot from outside the box misses to the left. Assisted by Gary Cahill.","period":2,"minute":92,"second":19,"sortKey":"2014-06-19 21:49:25","twitterImage":"","twitterHandle":"","twitterURL":"","twitterMediaURL":"","language":""},{"dateTime":"2014-06-19T21:45:31-04:00","formatedDateTime":"2014-06-19 21:45:31","comment":"Foul by Rickie Lambert (England).","period":2,"minute":89,"second":0,"sortKey":"2014-06-19 21:45:31","twitterImage":"","twitterHandle":"","twitterURL":"","twitterMediaURL":"","language":""},{"dateTime":"2014-06-19T21:45:30-04:00","formatedDateTime":"2014-06-19 21:45:30","comment":"Diego Godín (Uruguay) wins a free kick in the defensive half.","period":2,"minute":89,"second":0,"sortKey":"2014-06-19 21:45:30","twitterImage":"","twitterHandle":"","twitterURL":"","twitterMediaURL":"","language":""},{"dateTime":"2014-06-20T02:57:29-04:00","formatedDateTime":"2014-06-20 02:57:29","comment":"Substitution, Uruguay. Sebastián Coates replaces Luis Suárez because of an injury.","period":2,"minute":87,"second":5,"sortKey":"2014-06-20 02:57:29","twitterImage":"","twitterHandle":"","twitterURL":"","twitterMediaURL":"","language":""},{"dateTime":"2014-06-20T02:57:27-04:00","formatedDateTime":"2014-06-20 02:57:27","comment":"Delay over. They are ready to continue.","period":2,"minute":87,"second":0,"sortKey":"2014-06-20 02:57:27","twitterImage":"","twitterHandle":"","twitterURL":"","twitterMediaURL":"","language":""},{"dateTime":"2014-06-19T21:43:09-04:00","formatedDateTime":"2014-06-19 21:43:09","comment":"Delay in match Luis Suárez (Uruguay) because of an injury.","period":2,"minute":86,"second":38,"sortKey":"2014-06-19 21:43:09","twitterImage":"","twitterHandle":"","twitterURL":"","twitterMediaURL":"","language":""},{"dateTime":"2014-06-19T21:43:41-04:00","formatedDateTime":"2014-06-19 21:43:41","comment":"Substitution, England. Rickie Lambert replaces Jordan Henderson.","period":2,"minute":86,"second":8,"sortKey":"2014-06-19 21:43:41","twitterImage":"","twitterHandle":"","twitterURL":"","twitterMediaURL":"","language":""},{"dateTime":"2014-06-19T21:42:09-04:00","formatedDateTime":"2014-06-19 21:42:09","comment":"Wayne Rooney (England) wins a free kick on the left wing.","period":2,"minute":85,"second":38,"sortKey":"2014-06-19 21:42:09","twitterImage":"","twitterHandle":"","twitterURL":"","twitterMediaURL":"","language":""},{"dateTime":"2014-06-20T02:55:51-04:00","formatedDateTime":"2014-06-20 02:55:51","comment":"Foul by Christian Stuani (Uruguay).","period":2,"minute":85,"second":38,"sortKey":"2014-06-20 02:55:51","twitterImage":"","twitterHandle":"","twitterURL":"","twitterMediaURL":"","language":""},{"dateTime":"2014-06-20T02:54:43-04:00","formatedDateTime":"2014-06-20 02:54:43","comment":"Goal!  Uruguay 2, England 1. Luis Suárez (Uruguay) right footed shot from the right side of the box to the centre of the goal.","period":2,"minute":84,"second":1,"sortKey":"2014-06-20 02:54:43","twitterImage":"","twitterHandle":"","twitterURL":"","twitterMediaURL":"","language":""},{"dateTime":"2014-06-20T02:47:51-04:00","formatedDateTime":"2014-06-20 02:47:51","comment":"Corner,  Uruguay. Conceded by Gary Cahill.","period":2,"minute":81,"second":12,"sortKey":"2014-06-20 02:47:51","twitterImage":"","twitterHandle":"","twitterURL":"","twitterMediaURL":"","language":""},{"dateTime":"2014-06-20T02:47:03-04:00","formatedDateTime":"2014-06-20 02:47:03","comment":"Corner,  Uruguay. Conceded by Gary Cahill.","period":2,"minute":80,"second":42,"sortKey":"2014-06-20 02:47:03","twitterImage":"","twitterHandle":"","twitterURL":"","twitterMediaURL":"","language":""},{"dateTime":"2014-06-19T21:36:56-04:00","formatedDateTime":"2014-06-19 21:36:56","comment":"Daniel Sturridge (England) wins a free kick on the right wing.","period":2,"minute":79,"second":28,"sortKey":"2014-06-19 21:36:56","twitterImage":"","twitterHandle":"","twitterURL":"","twitterMediaURL":"","language":""},{"dateTime":"2014-06-19T21:36:57-04:00","formatedDateTime":"2014-06-19 21:36:57","comment":"Foul by Jorge Fucile (Uruguay).","period":2,"minute":79,"second":28,"sortKey":"2014-06-19 21:36:57","twitterImage":"","twitterHandle":"","twitterURL":"","twitterMediaURL":"","language":""},{"dateTime":"2014-06-19T21:35:02-04:00","formatedDateTime":"2014-06-19 21:35:02","comment":"Substitution, Uruguay. Jorge Fucile replaces Álvaro González.","period":2,"minute":77,"second":50,"sortKey":"2014-06-19 21:35:02","twitterImage":"","twitterHandle":"","twitterURL":"","twitterMediaURL":"","language":""},{"dateTime":"2014-06-19T21:33:58-04:00","formatedDateTime":"2014-06-19 21:33:58","comment":"Attempt saved. Daniel Sturridge (England) right footed shot from the centre of the box is saved in the bottom right corner. Assisted by Leighton Baines with a cross.","period":2,"minute":77,"second":8,"sortKey":"2014-06-19 21:33:58","twitterImage":"","twitterHandle":"","twitterURL":"","twitterMediaURL":"","language":""},{"dateTime":"2014-06-26T16:12:00-04:00","formatedDateTime":"2014-06-26 16:12:00","comment":"Goal!  Uruguay 1, England 1. Wayne Rooney (England) left footed shot from very close range to the bottom left corner. Assisted by Glen Johnson.","period":2,"minute":74,"second":41,"sortKey":"2014-06-26 16:12:00","twitterImage":"","twitterHandle":"","twitterURL":"","twitterMediaURL":"","language":""},{"dateTime":"2014-06-20T02:39:10-04:00","formatedDateTime":"2014-06-20 02:39:10","comment":"Attempt saved. Daniel Sturridge (England) left footed shot from outside the box is saved in the bottom right corner. Assisted by Glen Johnson.","period":2,"minute":73,"second":28,"sortKey":"2014-06-20 02:39:10","twitterImage":"","twitterHandle":"","twitterURL":"","twitterMediaURL":"","language":""},{"dateTime":"2014-06-19T21:29:42-04:00","formatedDateTime":"2014-06-19 21:29:42","comment":"Foul by Diego Godín (Uruguay).","period":2,"minute":73,"second":11,"sortKey":"2014-06-19 21:29:42","twitterImage":"","twitterHandle":"","twitterURL":"","twitterMediaURL":"","language":""},{"dateTime":"2014-06-19T21:29:42-04:00","formatedDateTime":"2014-06-19 21:29:42","comment":"Daniel Sturridge (England) wins a free kick on the right wing.","period":2,"minute":73,"second":11,"sortKey":"2014-06-19 21:29:42","twitterImage":"","twitterHandle":"","twitterURL":"","twitterMediaURL":"","language":""},{"dateTime":"2014-06-19T21:27:29-04:00","formatedDateTime":"2014-06-19 21:27:29","comment":"Foul by Wayne Rooney (England).","period":2,"minute":70,"second":59,"sortKey":"2014-06-19 21:27:29","twitterImage":"","twitterHandle":"","twitterURL":"","twitterMediaURL":"","language":""},{"dateTime":"2014-06-19T21:27:29-04:00","formatedDateTime":"2014-06-19 21:27:29","comment":"Egidio Arévalo Rios (Uruguay) wins a free kick in the attacking half.","period":2,"minute":70,"second":59,"sortKey":"2014-06-19 21:27:29","twitterImage":"","twitterHandle":"","twitterURL":"","twitterMediaURL":"","language":""},{"dateTime":"2014-06-19T21:26:46-04:00","formatedDateTime":"2014-06-19 21:26:46","comment":"Substitution, England. Adam Lallana replaces Danny Welbeck.","period":2,"minute":70,"second":19,"sortKey":"2014-06-19 21:26:46","twitterImage":"","twitterHandle":"","twitterURL":"","twitterMediaURL":"","language":""},{"dateTime":"2014-06-20T02:35:40-04:00","formatedDateTime":"2014-06-20 02:35:40","comment":"Foul by Gary Cahill (England).","period":2,"minute":69,"second":54,"sortKey":"2014-06-20 02:35:40","twitterImage":"","twitterHandle":"","twitterURL":"","twitterMediaURL":"","language":""},{"dateTime":"2014-06-20T02:35:39-04:00","formatedDateTime":"2014-06-20 02:35:39","comment":"Luis Suárez (Uruguay) wins a free kick on the left wing.","period":2,"minute":69,"second":54,"sortKey":"2014-06-20 02:35:39","twitterImage":"","twitterHandle":"","twitterURL":"","twitterMediaURL":"","language":""},{"dateTime":"2014-06-20T02:33:11-04:00","formatedDateTime":"2014-06-20 02:33:11","comment":"Attempt missed. Luis Suárez (Uruguay) right footed shot from long range on the right is too high. Assisted by Christian Stuani with a headed pass.","period":2,"minute":68,"second":4,"sortKey":"2014-06-20 02:33:11","twitterImage":"","twitterHandle":"","twitterURL":"","twitterMediaURL":"","language":""},{"dateTime":"2014-06-19T21:23:38-04:00","formatedDateTime":"2014-06-19 21:23:38","comment":"Steven Gerrard (England) is shown the yellow card for a bad foul.","period":2,"minute":67,"second":10,"sortKey":"2014-06-19 21:23:38","twitterImage":"","twitterHandle":"","twitterURL":"","twitterMediaURL":"","language":""},{"dateTime":"2014-06-19T21:23:33-04:00","formatedDateTime":"2014-06-19 21:23:33","comment":"Foul by Steven Gerrard (England).","period":2,"minute":67,"second":3,"sortKey":"2014-06-19 21:23:33","twitterImage":"","twitterHandle":"","twitterURL":"","twitterMediaURL":"","language":""},{"dateTime":"2014-06-19T21:23:33-04:00","formatedDateTime":"2014-06-19 21:23:33","comment":"Cristian Rodríguez (Uruguay) wins a free kick in the defensive half.","period":2,"minute":67,"second":3,"sortKey":"2014-06-19 21:23:33","twitterImage":"","twitterHandle":"","twitterURL":"","twitterMediaURL":"","language":""},{"dateTime":"2014-06-19T21:23:20-04:00","formatedDateTime":"2014-06-19 21:23:20","comment":"Substitution, Uruguay. Christian Stuani replaces Nicolás Lodeiro.","period":2,"minute":66,"second":35,"sortKey":"2014-06-19 21:23:20","twitterImage":"","twitterHandle":"","twitterURL":"","twitterMediaURL":"","language":""},{"dateTime":"2014-06-20T02:28:47-04:00","formatedDateTime":"2014-06-20 02:28:47","comment":"Phil Jagielka (England) wins a free kick in the defensive half.","period":2,"minute":64,"second":35,"sortKey":"2014-06-20 02:28:47","twitterImage":"","twitterHandle":"","twitterURL":"","twitterMediaURL":"","language":""},{"dateTime":"2014-06-20T02:28:49-04:00","formatedDateTime":"2014-06-20 02:28:49","comment":"Foul by Luis Suárez (Uruguay).","period":2,"minute":64,"second":35,"sortKey":"2014-06-20 02:28:49","twitterImage":"","twitterHandle":"","twitterURL":"","twitterMediaURL":"","language":""},{"dateTime":"2014-06-19T21:20:25-04:00","formatedDateTime":"2014-06-19 21:20:25","comment":"Substitution, England. Ross Barkley replaces Raheem Sterling.","period":2,"minute":63,"second":57,"sortKey":"2014-06-19 21:20:25","twitterImage":"","twitterHandle":"","twitterURL":"","twitterMediaURL":"","language":""},{"dateTime":"2014-06-20T02:27:59-04:00","formatedDateTime":"2014-06-20 02:27:59","comment":"Foul by Luis Suárez (Uruguay).","period":2,"minute":63,"second":44,"sortKey":"2014-06-20 02:27:59","twitterImage":"","twitterHandle":"","twitterURL":"","twitterMediaURL":"","language":""},{"dateTime":"2014-06-20T02:27:57-04:00","formatedDateTime":"2014-06-20 02:27:57","comment":"Gary Cahill (England) wins a free kick in the defensive half.","period":2,"minute":63,"second":44,"sortKey":"2014-06-20 02:27:57","twitterImage":"","twitterHandle":"","twitterURL":"","twitterMediaURL":"","language":""},{"dateTime":"2014-06-19T21:18:10-04:00","formatedDateTime":"2014-06-19 21:18:10","comment":"Delay over. They are ready to continue.","period":2,"minute":61,"second":42,"sortKey":"2014-06-19 21:18:10","twitterImage":"","twitterHandle":"","twitterURL":"","twitterMediaURL":"","language":""},{"dateTime":"2014-06-19T21:18:58-04:00","formatedDateTime":"2014-06-19 21:18:58","comment":"Delay in match Álvaro Pereira (Uruguay) because of an injury.","period":2,"minute":60,"second":46,"sortKey":"2014-06-19 21:18:58","twitterImage":"","twitterHandle":"","twitterURL":"","twitterMediaURL":"","language":""},{"dateTime":"2014-06-20T02:23:14-04:00","formatedDateTime":"2014-06-20 02:23:14","comment":"Attempt saved. Jordan Henderson (England) right footed shot from outside the box is saved in the bottom right corner. Assisted by Leighton Baines.","period":2,"minute":58,"second":43,"sortKey":"2014-06-20 02:23:14","twitterImage":"","twitterHandle":"","twitterURL":"","twitterMediaURL":"","language":""},{"dateTime":"2014-06-20T02:21:30-04:00","formatedDateTime":"2014-06-20 02:21:30","comment":"Wayne Rooney (England) wins a free kick on the left wing.","period":2,"minute":57,"second":55,"sortKey":"2014-06-20 02:21:30","twitterImage":"","twitterHandle":"","twitterURL":"","twitterMediaURL":"","language":""},{"dateTime":"2014-06-20T02:21:31-04:00","formatedDateTime":"2014-06-20 02:21:31","comment":"Foul by José María Giménez (Uruguay).","period":2,"minute":57,"second":55,"sortKey":"2014-06-20 02:21:31","twitterImage":"","twitterHandle":"","twitterURL":"","twitterMediaURL":"","language":""},{"dateTime":"2014-06-19T21:13:46-04:00","formatedDateTime":"2014-06-19 21:13:46","comment":"Martín Cáceres (Uruguay) wins a free kick in the defensive half.","period":2,"minute":56,"second":34,"sortKey":"2014-06-19 21:13:46","twitterImage":"","twitterHandle":"","twitterURL":"","twitterMediaURL":"","language":""},{"dateTime":"2014-06-19T21:13:51-04:00","formatedDateTime":"2014-06-19 21:13:51","comment":"Foul by Leighton Baines (England).","period":2,"minute":56,"second":34,"sortKey":"2014-06-19 21:13:51","twitterImage":"","twitterHandle":"","twitterURL":"","twitterMediaURL":"","language":""},{"dateTime":"2014-06-19T21:12:05-04:00","formatedDateTime":"2014-06-19 21:12:05","comment":"Delay over. They are ready to continue.","period":2,"minute":55,"second":38,"sortKey":"2014-06-19 21:12:05","twitterImage":"","twitterHandle":"","twitterURL":"","twitterMediaURL":"","language":""},{"dateTime":"2014-06-19T21:11:43-04:00","formatedDateTime":"2014-06-19 21:11:43","comment":"Delay in match Fernando Muslera (Uruguay) because of an injury.","period":2,"minute":55,"second":13,"sortKey":"2014-06-19 21:11:43","twitterImage":"","twitterHandle":"","twitterURL":"","twitterMediaURL":"","language":""},{"dateTime":"2014-06-19T21:26:31-04:00","formatedDateTime":"2014-06-19 21:26:31","comment":"Fernando Muslera (Uruguay) wins a free kick in the defensive half.","period":2,"minute":54,"second":25,"sortKey":"2014-06-19 21:26:31","twitterImage":"","twitterHandle":"","twitterURL":"","twitterMediaURL":"","language":""},{"dateTime":"2014-06-19T21:11:01-04:00","formatedDateTime":"2014-06-19 21:11:01","comment":"Foul by Danny Welbeck (England).","period":2,"minute":54,"second":25,"sortKey":"2014-06-19 21:11:01","twitterImage":"","twitterHandle":"","twitterURL":"","twitterMediaURL":"","language":""},{"dateTime":"2014-06-19T21:10:15-04:00","formatedDateTime":"2014-06-19 21:10:15","comment":"Glen Johnson (England) wins a free kick on the right wing.","period":2,"minute":53,"second":23,"sortKey":"2014-06-19 21:10:15","twitterImage":"","twitterHandle":"","twitterURL":"","twitterMediaURL":"","language":""},{"dateTime":"2014-06-19T21:11:55-04:00","formatedDateTime":"2014-06-19 21:11:55","comment":"Foul by Edinson Cavani (Uruguay).","period":2,"minute":53,"second":23,"sortKey":"2014-06-19 21:11:55","twitterImage":"","twitterHandle":"","twitterURL":"","twitterMediaURL":"","language":""},{"dateTime":"2014-06-20T02:17:40-04:00","formatedDateTime":"2014-06-20 02:17:40","comment":"Attempt saved. Wayne Rooney (England) left footed shot from the centre of the box is saved in the centre of the goal. Assisted by Leighton Baines with a cross.","period":2,"minute":53,"second":8,"sortKey":"2014-06-20 02:17:40","twitterImage":"","twitterHandle":"","twitterURL":"","twitterMediaURL":"","language":""},{"dateTime":"2014-06-20T02:16:09-04:00","formatedDateTime":"2014-06-20 02:16:09","comment":"Attempt missed. Edinson Cavani (Uruguay) right footed shot from the left side of the box misses to the right. Assisted by Nicolás Lodeiro.","period":2,"minute":51,"second":19,"sortKey":"2014-06-20 02:16:09","twitterImage":"","twitterHandle":"","twitterURL":"","twitterMediaURL":"","language":""},{"dateTime":"2014-06-20T02:14:44-04:00","formatedDateTime":"2014-06-20 02:14:44","comment":"Attempt missed. Luis Suárez (Uruguay) right footed shot from the right side of the box misses to the left. Assisted by Nicolás Lodeiro with a headed pass.","period":2,"minute":50,"second":0,"sortKey":"2014-06-20 02:14:44","twitterImage":"","twitterHandle":"","twitterURL":"","twitterMediaURL":"","language":""},{"dateTime":"2014-06-20T02:14:06-04:00","formatedDateTime":"2014-06-20 02:14:06","comment":"Corner,  Uruguay. Conceded by Steven Gerrard.","period":2,"minute":49,"second":19,"sortKey":"2014-06-20 02:14:06","twitterImage":"","twitterHandle":"","twitterURL":"","twitterMediaURL":"","language":""},{"dateTime":"2014-06-20T02:13:49-04:00","formatedDateTime":"2014-06-20 02:13:49","comment":"Attempt blocked. Álvaro González (Uruguay) left footed shot from outside the box is blocked. Assisted by Edinson Cavani.","period":2,"minute":49,"second":17,"sortKey":"2014-06-20 02:13:49","twitterImage":"","twitterHandle":"","twitterURL":"","twitterMediaURL":"","language":""},{"dateTime":"2014-06-19T21:04:28-04:00","formatedDateTime":"2014-06-19 21:04:28","comment":"Corner,  Uruguay. Conceded by Glen Johnson.","period":2,"minute":47,"second":59,"sortKey":"2014-06-19 21:04:28","twitterImage":"","twitterHandle":"","twitterURL":"","twitterMediaURL":"","language":""},{"dateTime":"2014-06-19T21:26:31-04:00","formatedDateTime":"2014-06-19 21:26:31","comment":"Foul by Daniel Sturridge (England).","period":2,"minute":47,"second":26,"sortKey":"2014-06-19 21:26:31","twitterImage":"","twitterHandle":"","twitterURL":"","twitterMediaURL":"","language":""},{"dateTime":"2014-06-19T21:04:36-04:00","formatedDateTime":"2014-06-19 21:04:36","comment":"Álvaro Pereira (Uruguay) wins a free kick in the defensive half.","period":2,"minute":47,"second":26,"sortKey":"2014-06-19 21:04:36","twitterImage":"","twitterHandle":"","twitterURL":"","twitterMediaURL":"","language":""},{"dateTime":"2014-06-19T21:01:27-04:00","formatedDateTime":"2014-06-19 21:01:27","comment":"Second Half begins Uruguay 1, England 0.","period":2,"minute":45,"second":0,"sortKey":"2014-06-19 21:01:27","twitterImage":"","twitterHandle":"","twitterURL":"","twitterMediaURL":"","language":""},{"dateTime":"2014-06-19T20:46:42-04:00","formatedDateTime":"2014-06-19 20:46:42","comment":"First Half ends, Uruguay 1, England 0.","period":1,"minute":45,"second":56,"sortKey":"2014-06-19 20:46:42","twitterImage":"","twitterHandle":"","twitterURL":"","twitterMediaURL":"","language":""},{"dateTime":"2014-06-19T20:44:58-04:00","formatedDateTime":"2014-06-19 20:44:58","comment":"Gary Cahill (England) wins a free kick in the attacking half.","period":1,"minute":44,"second":38,"sortKey":"2014-06-19 20:44:58","twitterImage":"","twitterHandle":"","twitterURL":"","twitterMediaURL":"","language":""},{"dateTime":"2014-06-19T20:44:54-04:00","formatedDateTime":"2014-06-19 20:44:54","comment":"Foul by Luis Suárez (Uruguay).","period":1,"minute":44,"second":38,"sortKey":"2014-06-19 20:44:54","twitterImage":"","twitterHandle":"","twitterURL":"","twitterMediaURL":"","language":""},{"dateTime":"2014-06-19T20:44:37-04:00","formatedDateTime":"2014-06-19 20:44:37","comment":"Leighton Baines (England) wins a free kick in the defensive half.","period":1,"minute":43,"second":47,"sortKey":"2014-06-19 20:44:37","twitterImage":"","twitterHandle":"","twitterURL":"","twitterMediaURL":"","language":""},{"dateTime":"2014-06-19T20:44:03-04:00","formatedDateTime":"2014-06-19 20:44:03","comment":"Foul by Álvaro González (Uruguay).","period":1,"minute":43,"second":47,"sortKey":"2014-06-19 20:44:03","twitterImage":"","twitterHandle":"","twitterURL":"","twitterMediaURL":"","language":""},{"dateTime":"2014-06-19T20:42:27-04:00","formatedDateTime":"2014-06-19 20:42:27","comment":"Corner,  England. Conceded by Egidio Arévalo Rios.","period":1,"minute":42,"second":9,"sortKey":"2014-06-19 20:42:27","twitterImage":"","twitterHandle":"","twitterURL":"","twitterMediaURL":"","language":""},{"dateTime":"2014-06-19T20:41:59-04:00","formatedDateTime":"2014-06-19 20:41:59","comment":"Corner,  England. Conceded by Álvaro González.","period":1,"minute":41,"second":42,"sortKey":"2014-06-19 20:41:59","twitterImage":"","twitterHandle":"","twitterURL":"","twitterMediaURL":"","language":""},{"dateTime":"2014-06-20T02:05:35-04:00","formatedDateTime":"2014-06-20 02:05:35","comment":"Corner,  England. Conceded by Martín Cáceres.","period":1,"minute":41,"second":0,"sortKey":"2014-06-20 02:05:35","twitterImage":"","twitterHandle":"","twitterURL":"","twitterMediaURL":"","language":""},{"dateTime":"2014-06-19T20:46:58-04:00","formatedDateTime":"2014-06-19 20:46:58","comment":"Corner,  England. Conceded by Fernando Muslera.","period":1,"minute":40,"second":9,"sortKey":"2014-06-19 20:46:58","twitterImage":"","twitterHandle":"","twitterURL":"","twitterMediaURL":"","language":""},{"dateTime":"2014-06-20T02:04:30-04:00","formatedDateTime":"2014-06-20 02:04:30","comment":"Attempt saved. Daniel Sturridge (England) left footed shot from the left side of the box is saved in the bottom left corner. Assisted by Wayne Rooney.","period":1,"minute":40,"second":6,"sortKey":"2014-06-20 02:04:30","twitterImage":"","twitterHandle":"","twitterURL":"","twitterMediaURL":"","language":""},{"dateTime":"2014-06-19T20:39:01-04:00","formatedDateTime":"2014-06-19 20:39:01","comment":"Goal!  Uruguay 1, England 0. Luis Suárez (Uruguay) header from the centre of the box to the bottom left corner. Assisted by Edinson Cavani with a through ball.","period":1,"minute":38,"second":11,"sortKey":"2014-06-19 20:39:01","twitterImage":"","twitterHandle":"","twitterURL":"","twitterMediaURL":"","language":""},{"dateTime":"2014-06-20T01:59:33-04:00","formatedDateTime":"2014-06-20 01:59:33","comment":"Attempt missed. Daniel Sturridge (England) left footed shot from outside the box is high and wide to the right. Assisted by Glen Johnson.","period":1,"minute":35,"second":43,"sortKey":"2014-06-20 01:59:33","twitterImage":"","twitterHandle":"","twitterURL":"","twitterMediaURL":"","language":""},{"dateTime":"2014-06-19T20:35:44-04:00","formatedDateTime":"2014-06-19 20:35:44","comment":"Wayne Rooney (England) wins a free kick in the attacking half.","period":1,"minute":35,"second":28,"sortKey":"2014-06-19 20:35:44","twitterImage":"","twitterHandle":"","twitterURL":"","twitterMediaURL":"","language":""},{"dateTime":"2014-06-19T20:47:28-04:00","formatedDateTime":"2014-06-19 20:47:28","comment":"Foul by Nicolás Lodeiro (Uruguay).","period":1,"minute":35,"second":28,"sortKey":"2014-06-19 20:47:28","twitterImage":"","twitterHandle":"","twitterURL":"","twitterMediaURL":"","language":""},{"dateTime":"2014-06-19T20:34:44-04:00","formatedDateTime":"2014-06-19 20:34:44","comment":"Foul by Leighton Baines (England).","period":1,"minute":34,"second":15,"sortKey":"2014-06-19 20:34:44","twitterImage":"","twitterHandle":"","twitterURL":"","twitterMediaURL":"","language":""},{"dateTime":"2014-06-19T20:34:45-04:00","formatedDateTime":"2014-06-19 20:34:45","comment":"Álvaro González (Uruguay) wins a free kick in the defensive half.","period":1,"minute":34,"second":15,"sortKey":"2014-06-19 20:34:45","twitterImage":"","twitterHandle":"","twitterURL":"","twitterMediaURL":"","language":""},{"dateTime":"2014-06-19T20:33:31-04:00","formatedDateTime":"2014-06-19 20:33:31","comment":"Foul by Raheem Sterling (England).","period":1,"minute":32,"second":13,"sortKey":"2014-06-19 20:33:31","twitterImage":"","twitterHandle":"","twitterURL":"","twitterMediaURL":"","language":""},{"dateTime":"2014-06-19T20:33:32-04:00","formatedDateTime":"2014-06-19 20:33:32","comment":"Cristian Rodríguez (Uruguay) wins a free kick in the attacking half.","period":1,"minute":32,"second":13,"sortKey":"2014-06-19 20:33:32","twitterImage":"","twitterHandle":"","twitterURL":"","twitterMediaURL":"","language":""},{"dateTime":"2014-06-19T20:31:58-04:00","formatedDateTime":"2014-06-19 20:31:58","comment":"Foul by Wayne Rooney (England).","period":1,"minute":31,"second":32,"sortKey":"2014-06-19 20:31:58","twitterImage":"","twitterHandle":"","twitterURL":"","twitterMediaURL":"","language":""},{"dateTime":"2014-06-19T20:31:58-04:00","formatedDateTime":"2014-06-19 20:31:58","comment":"Martín Cáceres (Uruguay) wins a free kick in the defensive half.","period":1,"minute":31,"second":32,"sortKey":"2014-06-19 20:31:58","twitterImage":"","twitterHandle":"","twitterURL":"","twitterMediaURL":"","language":""},{"dateTime":"2014-06-19T20:33:14-04:00","formatedDateTime":"2014-06-19 20:33:14","comment":"Wayne Rooney (England) hits the bar with a header from very close range. Assisted by Steven Gerrard with a cross following a set piece situation.","period":1,"minute":30,"second":54,"sortKey":"2014-06-19 20:33:14","twitterImage":"","twitterHandle":"","twitterURL":"","twitterMediaURL":"","language":""},{"dateTime":"2014-06-19T20:30:11-04:00","formatedDateTime":"2014-06-19 20:30:11","comment":"Foul by Martín Cáceres (Uruguay).","period":1,"minute":29,"second":55,"sortKey":"2014-06-19 20:30:11","twitterImage":"","twitterHandle":"","twitterURL":"","twitterMediaURL":"","language":""},{"dateTime":"2014-06-19T20:30:10-04:00","formatedDateTime":"2014-06-19 20:30:10","comment":"Danny Welbeck (England) wins a free kick on the left wing.","period":1,"minute":29,"second":55,"sortKey":"2014-06-19 20:30:10","twitterImage":"","twitterHandle":"","twitterURL":"","twitterMediaURL":"","language":""},{"dateTime":"2014-06-19T20:46:54-04:00","formatedDateTime":"2014-06-19 20:46:54","comment":"Foul by Diego Godín (Uruguay).","period":1,"minute":28,"second":18,"sortKey":"2014-06-19 20:46:54","twitterImage":"","twitterHandle":"","twitterURL":"","twitterMediaURL":"","language":""},{"dateTime":"2014-06-19T20:46:54-04:00","formatedDateTime":"2014-06-19 20:46:54","comment":"Daniel Sturridge (England) wins a free kick on the right wing.","period":1,"minute":28,"second":18,"sortKey":"2014-06-19 20:46:54","twitterImage":"","twitterHandle":"","twitterURL":"","twitterMediaURL":"","language":""},{"dateTime":"2014-06-19T20:27:07-04:00","formatedDateTime":"2014-06-19 20:27:07","comment":"Attempt missed. Edinson Cavani (Uruguay) right footed shot from the centre of the box is close, but misses the top right corner. Assisted by Luis Suárez following a corner.","period":1,"minute":26,"second":29,"sortKey":"2014-06-19 20:27:07","twitterImage":"","twitterHandle":"","twitterURL":"","twitterMediaURL":"","language":""},{"dateTime":"2014-06-20T02:48:37-04:00","formatedDateTime":"2014-06-20 02:48:37","comment":"Corner,  Uruguay. Conceded by Gary Cahill.","period":1,"minute":25,"second":59,"sortKey":"2014-06-20 02:48:37","twitterImage":"","twitterHandle":"","twitterURL":"","twitterMediaURL":"","language":""},{"dateTime":"2014-06-19T20:24:41-04:00","formatedDateTime":"2014-06-19 20:24:41","comment":"Foul by Raheem Sterling (England).","period":1,"minute":24,"second":25,"sortKey":"2014-06-19 20:24:41","twitterImage":"","twitterHandle":"","twitterURL":"","twitterMediaURL":"","language":""},{"dateTime":"2014-06-19T20:24:41-04:00","formatedDateTime":"2014-06-19 20:24:41","comment":"Álvaro Pereira (Uruguay) wins a free kick on the left wing.","period":1,"minute":24,"second":25,"sortKey":"2014-06-19 20:24:41","twitterImage":"","twitterHandle":"","twitterURL":"","twitterMediaURL":"","language":""},{"dateTime":"2014-06-19T20:22:51-04:00","formatedDateTime":"2014-06-19 20:22:51","comment":"Offside, Uruguay. Álvaro González tries a through ball, but Luis Suárez is caught offside.","period":1,"minute":22,"second":35,"sortKey":"2014-06-19 20:22:51","twitterImage":"","twitterHandle":"","twitterURL":"","twitterMediaURL":"","language":""},{"dateTime":"2014-06-19T20:20:16-04:00","formatedDateTime":"2014-06-19 20:20:16","comment":"Offside, England. Glen Johnson tries a through ball, but Daniel Sturridge is caught offside.","period":1,"minute":19,"second":46,"sortKey":"2014-06-19 20:20:16","twitterImage":"","twitterHandle":"","twitterURL":"","twitterMediaURL":"","language":""},{"dateTime":"2014-06-20T01:41:57-04:00","formatedDateTime":"2014-06-20 01:41:57","comment":"Foul by Raheem Sterling (England).","period":1,"minute":18,"second":59,"sortKey":"2014-06-20 01:41:57","twitterImage":"","twitterHandle":"","twitterURL":"","twitterMediaURL":"","language":""},{"dateTime":"2014-06-20T01:41:58-04:00","formatedDateTime":"2014-06-20 01:41:58","comment":"José María Giménez (Uruguay) wins a free kick in the defensive half.","period":1,"minute":18,"second":59,"sortKey":"2014-06-20 01:41:58","twitterImage":"","twitterHandle":"","twitterURL":"","twitterMediaURL":"","language":""},{"dateTime":"2014-06-19T20:16:59-04:00","formatedDateTime":"2014-06-19 20:16:59","comment":"Corner,  England. Conceded by Álvaro Pereira.","period":1,"minute":16,"second":43,"sortKey":"2014-06-19 20:16:59","twitterImage":"","twitterHandle":"","twitterURL":"","twitterMediaURL":"","language":""},{"dateTime":"2014-06-20T01:40:02-04:00","formatedDateTime":"2014-06-20 01:40:02","comment":"Attempt blocked. Daniel Sturridge (England) left footed shot from the right side of the box is blocked. Assisted by Jordan Henderson.","period":1,"minute":16,"second":41,"sortKey":"2014-06-20 01:40:02","twitterImage":"","twitterHandle":"","twitterURL":"","twitterMediaURL":"","language":""},{"dateTime":"2014-06-20T01:37:55-04:00","formatedDateTime":"2014-06-20 01:37:55","comment":"Attempt missed. Cristian Rodríguez (Uruguay) left footed shot from the left side of the box is just a bit too high.","period":1,"minute":14,"second":50,"sortKey":"2014-06-20 01:37:55","twitterImage":"","twitterHandle":"","twitterURL":"","twitterMediaURL":"","language":""},{"dateTime":"2014-06-20T01:36:43-04:00","formatedDateTime":"2014-06-20 01:36:43","comment":"Gary Cahill (England) wins a free kick in the defensive half.","period":1,"minute":14,"second":21,"sortKey":"2014-06-20 01:36:43","twitterImage":"","twitterHandle":"","twitterURL":"","twitterMediaURL":"","language":""},{"dateTime":"2014-06-20T01:36:44-04:00","formatedDateTime":"2014-06-20 01:36:44","comment":"Foul by Cristian Rodríguez (Uruguay).","period":1,"minute":14,"second":21,"sortKey":"2014-06-20 01:36:44","twitterImage":"","twitterHandle":"","twitterURL":"","twitterMediaURL":"","language":""},{"dateTime":"2014-06-20T01:36:01-04:00","formatedDateTime":"2014-06-20 01:36:01","comment":"Offside, Uruguay. Martín Cáceres tries a through ball, but Luis Suárez is caught offside.","period":1,"minute":13,"second":45,"sortKey":"2014-06-20 01:36:01","twitterImage":"","twitterHandle":"","twitterURL":"","twitterMediaURL":"","language":""},{"dateTime":"2014-06-19T20:13:01-04:00","formatedDateTime":"2014-06-19 20:13:01","comment":"Wayne Rooney (England) wins a free kick in the defensive half.","period":1,"minute":12,"second":44,"sortKey":"2014-06-19 20:13:01","twitterImage":"","twitterHandle":"","twitterURL":"","twitterMediaURL":"","language":""},{"dateTime":"2014-06-19T20:13:00-04:00","formatedDateTime":"2014-06-19 20:13:00","comment":"Foul by Egidio Arévalo Rios (Uruguay).","period":1,"minute":12,"second":44,"sortKey":"2014-06-19 20:13:00","twitterImage":"","twitterHandle":"","twitterURL":"","twitterMediaURL":"","language":""},{"dateTime":"2014-06-19T20:10:19-04:00","formatedDateTime":"2014-06-19 20:10:19","comment":"Foul by Martín Cáceres (Uruguay).","period":1,"minute":9,"second":55,"sortKey":"2014-06-19 20:10:19","twitterImage":"","twitterHandle":"","twitterURL":"","twitterMediaURL":"","language":""},{"dateTime":"2014-06-19T20:10:19-04:00","formatedDateTime":"2014-06-19 20:10:19","comment":"Danny Welbeck (England) wins a free kick in the defensive half.","period":1,"minute":9,"second":55,"sortKey":"2014-06-19 20:10:19","twitterImage":"","twitterHandle":"","twitterURL":"","twitterMediaURL":"","language":""},{"dateTime":"2014-06-19T20:09:58-04:00","formatedDateTime":"2014-06-19 20:09:58","comment":"Attempt missed. Wayne Rooney (England) right footed shot from outside the box is close, but misses to the left from a direct free kick.","period":1,"minute":9,"second":19,"sortKey":"2014-06-19 20:09:58","twitterImage":"","twitterHandle":"","twitterURL":"","twitterMediaURL":"","language":""},{"dateTime":"2014-06-19T20:08:41-04:00","formatedDateTime":"2014-06-19 20:08:41","comment":"Diego Godín (Uruguay) is shown the yellow card for hand ball.","period":1,"minute":8,"second":24,"sortKey":"2014-06-19 20:08:41","twitterImage":"","twitterHandle":"","twitterURL":"","twitterMediaURL":"","language":""},{"dateTime":"2014-06-19T20:10:12-04:00","formatedDateTime":"2014-06-19 20:10:12","comment":"Hand ball by Diego Godín (Uruguay).","period":1,"minute":8,"second":21,"sortKey":"2014-06-19 20:10:12","twitterImage":"","twitterHandle":"","twitterURL":"","twitterMediaURL":"","language":""},{"dateTime":"2014-06-19T20:10:11-04:00","formatedDateTime":"2014-06-19 20:10:11","comment":"Foul by Nicolás Lodeiro (Uruguay).","period":1,"minute":6,"second":20,"sortKey":"2014-06-19 20:10:11","twitterImage":"","twitterHandle":"","twitterURL":"","twitterMediaURL":"","language":""},{"dateTime":"2014-06-19T20:10:11-04:00","formatedDateTime":"2014-06-19 20:10:11","comment":"Raheem Sterling (England) wins a free kick in the attacking half.","period":1,"minute":6,"second":20,"sortKey":"2014-06-19 20:10:11","twitterImage":"","twitterHandle":"","twitterURL":"","twitterMediaURL":"","language":""},{"dateTime":"2014-06-19T20:05:04-04:00","formatedDateTime":"2014-06-19 20:05:04","comment":"Offside, Uruguay. Álvaro González tries a through ball, but Edinson Cavani is caught offside.","period":1,"minute":4,"second":42,"sortKey":"2014-06-19 20:05:04","twitterImage":"","twitterHandle":"","twitterURL":"","twitterMediaURL":"","language":""},{"dateTime":"2014-06-20T02:49:25-04:00","formatedDateTime":"2014-06-20 02:49:25","comment":"Corner,  Uruguay. Conceded by Jordan Henderson.","period":1,"minute":4,"second":19,"sortKey":"2014-06-20 02:49:25","twitterImage":"","twitterHandle":"","twitterURL":"","twitterMediaURL":"","language":""},{"dateTime":"2014-06-20T02:49:14-04:00","formatedDateTime":"2014-06-20 02:49:14","comment":"Corner,  Uruguay. Conceded by Joe Hart.","period":1,"minute":3,"second":45,"sortKey":"2014-06-20 02:49:14","twitterImage":"","twitterHandle":"","twitterURL":"","twitterMediaURL":"","language":""},{"dateTime":"2014-06-19T20:00:14-04:00","formatedDateTime":"2014-06-19 20:00:14","comment":"First Half begins.","period":1,"minute":0,"second":0,"sortKey":"2014-06-19 20:00:14","twitterImage":"","twitterHandle":"","twitterURL":"","twitterMediaURL":"","language":""},{"dateTime":"2014-06-19T20:05:33-04:00","formatedDateTime":"2014-06-19 20:05:33","comment":"Lineups are announced and players are warming up.","period":1,"minute":0,"second":0,"sortKey":"2014-06-19 20:05:33","twitterImage":"","twitterHandle":"","twitterURL":"","twitterMediaURL":"","language":""}]