{"individualGameStat":[{"accurate_pass":19,"touches":39,"duel_lost":9,"duel_won":4,"fouls":4,"game_started":1,"goal_assist":0,"goals":0,"mins_played":90,"saves":0,"red_card":0,"shot_fastbreak":0,"total_scoring_att":0,"yellow_card":0,"opposingTeam":{"country":"Japan","abbreviation":"JPN","optaid":"t1266"}},{"accurate_pass":19,"touches":39,"duel_lost":9,"duel_won":4,"fouls":4,"game_started":1,"goal_assist":0,"goals":0,"mins_played":90,"saves":0,"red_card":0,"shot_fastbreak":0,"total_scoring_att":0,"yellow_card":0,"opposingTeam":{"country":"Japan","abbreviation":"JPN","optaid":"t1266"}}],"info":{"id":"p149491","name":"Alexander Mejía","position":"Midfielder","dob":"1988-07-11 00:00:00","placeOfBirth":"Barranquilla","heightMetric":177,"heightEnglish":580,"weightMetric":77,"weightEnglish":169,"goal":0,"goalAllowed":"","teamName":"Colombia","teamID":"t832"},"totalStat":{"accurate_pass":38,"touches":78,"duel_lost":18,"duel_won":8,"fouls":8,"game_started":2,"goal_assist":0,"goals":0,"mins_played":180,"saves":0,"red_card":0,"shot_fastbreak":0,"total_scoring_att":0,"yellow_card":0}}