{"individualGameStat":[{"accurate_pass":55,"touches":77,"duel_lost":3,"duel_won":2,"fouls":1,"game_started":1,"goal_assist":0,"goals":0,"mins_played":90,"saves":0,"red_card":0,"shot_fastbreak":0,"total_scoring_att":1,"yellow_card":0,"opposingTeam":{"country":"Portugal","abbreviation":"POR","optaid":"t359"}},{"accurate_pass":45,"touches":62,"duel_lost":7,"duel_won":4,"fouls":4,"game_started":1,"goal_assist":0,"goals":0,"mins_played":90,"saves":0,"red_card":0,"shot_fastbreak":0,"total_scoring_att":0,"yellow_card":1,"opposingTeam":{"country":"Germany","abbreviation":"GER","optaid":"t357"}}],"info":{"id":"p15517","name":"Kyle Beckerman","position":"Midfielder","dob":"1982-04-23 00:00:00","placeOfBirth":"Crofton","heightMetric":181,"heightEnglish":593,"weightMetric":75,"weightEnglish":165,"goal":1,"goalAllowed":"","teamName":"USA","teamID":"t596"},"totalStat":{"accurate_pass":100,"touches":139,"duel_lost":10,"duel_won":6,"fouls":5,"game_started":2,"goal_assist":0,"goals":0,"mins_played":180,"saves":0,"red_card":0,"shot_fastbreak":0,"total_scoring_att":1,"yellow_card":1}}