{"individualGameStat":[{"accurate_pass":49,"touches":71,"duel_lost":8,"duel_won":5,"fouls":1,"game_started":1,"goal_assist":0,"goals":0,"mins_played":90,"saves":0,"red_card":0,"shot_fastbreak":0,"total_scoring_att":1,"yellow_card":1,"opposingTeam":{"country":"Bosnia and Herzegovina","abbreviation":"BIH","optaid":"t537"}},{"accurate_pass":41,"touches":62,"duel_lost":3,"duel_won":5,"fouls":1,"game_started":1,"goal_assist":0,"goals":0,"mins_played":90,"saves":0,"red_card":0,"shot_fastbreak":0,"total_scoring_att":1,"yellow_card":0,"opposingTeam":{"country":"Argentina","abbreviation":"ARG","optaid":"t632"}}],"info":{"id":"p28495","name":"John Obi Mikel","position":"Midfielder","dob":"1987-04-22 00:00:00","placeOfBirth":"Jos","heightMetric":188,"heightEnglish":616,"weightMetric":83,"weightEnglish":182,"goal":4,"goalAllowed":"","teamName":"Nigeria","teamID":"t1216"},"totalStat":{"accurate_pass":90,"touches":133,"duel_lost":11,"duel_won":10,"fouls":2,"game_started":2,"goal_assist":0,"goals":0,"mins_played":180,"saves":0,"red_card":0,"shot_fastbreak":0,"total_scoring_att":2,"yellow_card":1}}