{"individualGameStat":[{"accurate_pass":0,"touches":0,"duel_lost":0,"duel_won":0,"fouls":0,"game_started":0,"goal_assist":0,"goals":0,"mins_played":0,"saves":0,"red_card":0,"shot_fastbreak":0,"total_scoring_att":0,"yellow_card":0,"opposingTeam":{"country":"Spain","abbreviation":"ESP","optaid":"t118"}},{"accurate_pass":0,"touches":0,"duel_lost":0,"duel_won":0,"fouls":0,"game_started":0,"goal_assist":0,"goals":0,"mins_played":0,"saves":0,"red_card":0,"shot_fastbreak":0,"total_scoring_att":0,"yellow_card":0,"opposingTeam":{"country":"Spain","abbreviation":"ESP","optaid":"t118"}}],"info":{"id":"p44998","name":"Dario Vidosic","position":"Midfielder","dob":"1987-04-08 00:00:00","placeOfBirth":"Osijek","heightMetric":184,"heightEnglish":603,"weightMetric":74,"weightEnglish":163,"goal":2,"goalAllowed":"","teamName":"Australia","teamID":"t575"},"totalStat":{"accurate_pass":0,"touches":0,"duel_lost":0,"duel_won":0,"fouls":0,"game_started":0,"goal_assist":0,"goals":0,"mins_played":0,"saves":0,"red_card":0,"shot_fastbreak":0,"total_scoring_att":0,"yellow_card":0}}