{"individualGameStat":[{"accurate_pass":17,"touches":31,"duel_lost":4,"duel_won":2,"fouls":2,"game_started":1,"goal_assist":0,"goals":1,"mins_played":90,"saves":0,"red_card":0,"shot_fastbreak":0,"total_scoring_att":4,"yellow_card":0,"opposingTeam":{"country":"Costa Rica","abbreviation":"CRC","optaid":"t838"}},{"accurate_pass":19,"touches":32,"duel_lost":8,"duel_won":2,"fouls":1,"game_started":1,"goal_assist":1,"goals":0,"mins_played":90,"saves":0,"red_card":0,"shot_fastbreak":0,"total_scoring_att":2,"yellow_card":0,"opposingTeam":{"country":"England","abbreviation":"ENG","optaid":"t114"}},{"accurate_pass":20,"touches":37,"duel_lost":4,"duel_won":2,"fouls":2,"game_started":1,"goal_assist":0,"goals":0,"mins_played":90,"saves":0,"red_card":0,"shot_fastbreak":0,"total_scoring_att":2,"yellow_card":0,"opposingTeam":{"country":"Italy","abbreviation":"ITA","optaid":"t119"}},{"accurate_pass":24,"touches":53,"duel_lost":10,"duel_won":4,"fouls":3,"game_started":1,"goal_assist":0,"goals":0,"mins_played":90,"saves":0,"red_card":0,"shot_fastbreak":0,"total_scoring_att":5,"yellow_card":0,"opposingTeam":{"country":"Colombia","abbreviation":"COL","optaid":"t832"}}],"info":{"id":"p40720","name":"Edinson Cavani","position":"Forward","dob":"1987-02-14 00:00:00","placeOfBirth":"Salto","heightMetric":184,"heightEnglish":603,"weightMetric":71,"weightEnglish":156,"goal":22,"goalAllowed":"","teamName":"Uruguay","teamID":"t837"},"totalStat":{"accurate_pass":80,"touches":153,"duel_lost":26,"duel_won":10,"fouls":8,"game_started":4,"goal_assist":1,"goals":1,"mins_played":360,"saves":0,"red_card":0,"shot_fastbreak":0,"total_scoring_att":13,"yellow_card":0}}