{"individualGameStat":[{"accurate_pass":0,"touches":0,"duel_lost":0,"duel_won":0,"fouls":0,"game_started":0,"goal_assist":0,"goals":0,"mins_played":0,"saves":0,"red_card":0,"shot_fastbreak":0,"total_scoring_att":0,"yellow_card":0,"opposingTeam":{"country":"Belgium","abbreviation":"BEL","optaid":"t360"}},{"accurate_pass":30,"touches":69,"duel_lost":5,"duel_won":8,"fouls":1,"game_started":1,"goal_assist":0,"goals":0,"mins_played":90,"saves":0,"red_card":0,"shot_fastbreak":0,"total_scoring_att":0,"yellow_card":0,"opposingTeam":{"country":"Korea","abbreviation":"KOR","optaid":"t1041"}},{"accurate_pass":30,"touches":61,"duel_lost":5,"duel_won":3,"fouls":4,"game_started":1,"goal_assist":0,"goals":0,"mins_played":90,"saves":0,"red_card":0,"shot_fastbreak":0,"total_scoring_att":1,"yellow_card":1,"opposingTeam":{"country":"Russia","abbreviation":"RUS","optaid":"t536"}},{"accurate_pass":0,"touches":0,"duel_lost":0,"duel_won":0,"fouls":0,"game_started":0,"goal_assist":0,"goals":0,"mins_played":0,"saves":0,"red_card":0,"shot_fastbreak":0,"total_scoring_att":0,"yellow_card":0,"opposingTeam":{"country":"Germany","abbreviation":"GER","optaid":"t357"}}],"info":{"id":"p34694","name":"Djamel Mesbah","position":"Defender","dob":"1984-10-09 00:00:00","placeOfBirth":"Zighoud Youcef","heightMetric":179,"heightEnglish":587,"weightMetric":75,"weightEnglish":165,"goal":0,"goalAllowed":"","teamName":"Algeria","teamID":"t1215"},"totalStat":{"accurate_pass":60,"touches":130,"duel_lost":10,"duel_won":11,"fouls":5,"game_started":2,"goal_assist":0,"goals":0,"mins_played":180,"saves":0,"red_card":0,"shot_fastbreak":0,"total_scoring_att":1,"yellow_card":1}}