{"isGameLive":false,"IDGame":"f731810","type":"Result","time":"20140625T170000+0100","attendence":"48011","venue":"Arena Fonte Nova","pool":"F","round":"1","firstHalfTime":"48","secondHalfTime":"48","matchTime":"93","matchOfficialFirstName":"Carlos","matchOfficialLastName":"Velasco Carballo","home":{"IDTeam":"t537","abbreviation":"BIH","score":"3","name":"Bosnia and Herzegovina","total":{"redCard":0,"yellowCard":1,"shotOnGoal":12,"tackle":15,"foulCount":20,"offSide":1,"wonCorner":6,"save":1},"goal":[{"period":"FirstHalf","time":"23","timeStamp":"20140625T172253+0100","type":"Goal","IDPlayer":"p42544","playerFirstName":"Edin","playerLastName":"Dzeko"},{"period":"SecondHalf","time":"59","timeStamp":"20140625T181721+0100","type":"Goal","IDPlayer":"p46696","playerFirstName":"Miralem","playerLastName":"Pjanic"},{"period":"SecondHalf","time":"83","timeStamp":"20140625T184116+0100","type":"Goal","IDPlayer":"p67140","playerFirstName":"Avdija","playerLastName":"Vrsajevic"}],"booking":[{"period":"SecondHalf","time":"77","timeStamp":"20140625T183537+0100","card":"Yellow","cardType":"Yellow","IDPlayer":"p87447","playerFirstName":"Muhamed","playerLastName":"Besic"}],"substitution":[{"offFirstName":"Anel","offLastName":"Hadzic","onFirstName":"Ognjen","onLastName":"Vranjes","position":2,"reason":"Tactical","time":61},{"offFirstName":"Tino","offLastName":"Susic","onFirstName":"Sejad","onLastName":"Salihovic","position":3,"reason":"Tactical","time":79},{"offFirstName":"Edin","offLastName":"Dzeko","onFirstName":"Edin","onLastName":"Visca","position":4,"reason":"Tactical","time":84}],"startingLineUp":{"starting":[{"id":"p40349","number":"1","position":"Goalkeeper","status":"Start","name":{"firstName":"Asmir","lastName":"Begovic"}},{"id":"p20301","number":"4","position":"Defender","status":"Start","name":{"firstName":"Emir","lastName":"Spahic"}},{"id":"p67140","number":"2","position":"Defender","status":"Start","name":{"firstName":"Avdija","lastName":"Vrsajevic"}},{"id":"p70496","number":"15","position":"Defender","status":"Start","name":{"firstName":"Toni","lastName":"Sunjic"}},{"id":"p111457","number":"5","position":"Defender","status":"Start","name":{"firstName":"Sead","lastName":"Kolasinac"}},{"id":"p46696","number":"8","position":"Midfielder","status":"Start","name":{"firstName":"Miralem","lastName":"Pjanic"}},{"id":"p43692","number":"21","position":"Midfielder","status":"Start","name":{"firstName":"Anel","lastName":"Hadzic"}},{"id":"p85665","number":"14","position":"Midfielder","status":"Start","name":{"firstName":"Tino","lastName":"Susic"}},{"id":"p87447","number":"7","position":"Midfielder","status":"Start","name":{"firstName":"Muhamed","lastName":"Besic"}},{"id":"p42544","number":"11","position":"Forward","status":"Start","name":{"firstName":"Edin","lastName":"Dzeko"}},{"id":"p18695","number":"9","position":"Forward","status":"Start","name":{"firstName":"Vedad","lastName":"Ibisevic"}}],"substitution":[{"id":"p52049","number":"16","position":"Defender","status":"Sub","name":{"firstName":"Senad","lastName":"Lulic"}},{"id":"p18771","number":"23","position":"Forward","status":"Sub","name":{"firstName":"Sejad","lastName":"Salihovic"}},{"id":"p70953","number":"22","position":"Goalkeeper","status":"Sub","name":{"firstName":"Asmir","lastName":"Avdukic"}},{"id":"p64657","number":"6","position":"Defender","status":"Sub","name":{"firstName":"Ognjen","lastName":"Vranjes"}},{"id":"p20716","number":"12","position":"Goalkeeper","status":"Sub","name":{"firstName":"Jasmin","lastName":"Fejzic"}},{"id":"p28188","number":"18","position":"Midfielder","status":"Sub","name":{"firstName":"Haris","lastName":"Medunjanin"}},{"id":"p66841","number":"13","position":"Midfielder","status":"Sub","name":{"firstName":"Mensur","lastName":"Mujdza"}},{"id":"p82664","number":"19","position":"Midfielder","status":"Sub","name":{"firstName":"Edin","lastName":"Visca"}},{"id":"p69147","number":"3","position":"Defender","status":"Sub","name":{"firstName":"Ermin","lastName":"Bicakcic"}},{"id":"p37118","number":"17","position":"Midfielder","status":"Sub","name":{"firstName":"Senijad","lastName":"Ibricic"}},{"id":"p16050","number":"10","position":"Midfielder","status":"Sub","name":{"firstName":"Zvjezdan","lastName":"Misimovic"}},{"id":"p69887","number":"20","position":"Midfielder","status":"Sub","name":{"firstName":"Izet","lastName":"Hajrovic"}}]},"shootout":[]},"away":{"IDTeam":"t1042","abbreviation":"IRN","score":"1","name":"Iran","total":{"redCard":0,"yellowCard":1,"shotOnGoal":7,"tackle":20,"foulCount":17,"offSide":8,"wonCorner":5,"save":2},"goal":[{"period":"SecondHalf","time":"82","timeStamp":"20140625T184020+0100","type":"Goal","IDPlayer":"p41071","playerFirstName":"Reza","playerLastName":"Ghoochannejhad"},{},{"IDPlayer":"p36803","playerFirstName":"Javad","playerLastName":"Nekounam"},{"IDPlayer":"p155072","playerFirstName":"Khosro","playerLastName":"Heydari"}],"booking":[{"period":"SecondHalf","time":"88","timeStamp":"20140625T184556+0100","card":"Yellow","cardType":"Yellow","IDPlayer":"p179950","playerFirstName":"Kirim","playerLastName":"Ansarifard"}],"substitution":[{"offFirstName":"Masoud","offLastName":"Shojaei","onFirstName":"Khosro","onLastName":"Heydari","position":3,"reason":"Tactical","time":45},{"offFirstName":"Ehsan","offLastName":"Hajsafi","onFirstName":"Alireza","onLastName":"Jahanbakhsh","position":4,"reason":"Tactical","time":63},{"offFirstName":"Ashkan","offLastName":"Dejagah","onFirstName":"Kirim","onLastName":"Ansarifard","position":4,"reason":"Tactical","time":68}],"startingLineUp":{"starting":[{"id":"p111674","number":"12","position":"Goalkeeper","status":"Start","name":{"firstName":"Alireza","lastName":"Haghighi"}},{"id":"p156604","number":"23","position":"Defender","status":"Start","name":{"firstName":"Mehrdad","lastName":"Pooladi"}},{"id":"p155084","number":"15","position":"Defender","status":"Start","name":{"firstName":"Pejman","lastName":"Montazeri"}},{"id":"p37197","number":"5","position":"Defender","status":"Start","name":{"firstName":"Amir Hossein","lastName":"Sadeqi"}},{"id":"p183059","number":"4","position":"Defender","status":"Start","name":{"firstName":"Jalal","lastName":"Hosseini"}},{"id":"p18427","number":"21","position":"Midfielder","status":"Start","name":{"firstName":"Ashkan","lastName":"Dejagah"}},{"id":"p49529","number":"3","position":"Midfielder","status":"Start","name":{"firstName":"Ehsan","lastName":"Hajsafi"}},{"id":"p37036","number":"14","position":"Midfielder","status":"Start","name":{"firstName":"Andranik","lastName":"Teymourian"}},{"id":"p37198","number":"7","position":"Midfielder","status":"Start","name":{"firstName":"Masoud","lastName":"Shojaei"}},{"id":"p36803","number":"6","position":"Midfielder","status":"Start","name":{"firstName":"Javad","lastName":"Nekounam"}},{"id":"p41071","number":"16","position":"Forward","status":"Start","name":{"firstName":"Reza","lastName":"Ghoochannejhad"}}],"substitution":[{"id":"p82845","number":"20","position":"Defender","status":"Sub","name":{"firstName":"Steven","lastName":"Beitashour"}},{"id":"p180956","number":"1","position":"Goalkeeper","status":"Sub","name":{"firstName":"Rahman","lastName":"Ahmadi"}},{"id":"p155072","number":"2","position":"Defender","status":"Sub","name":{"firstName":"Khosro","lastName":"Heydari"}},{"id":"p184493","number":"13","position":"Defender","status":"Sub","name":{"firstName":"Hossein","lastName":"Mahini"}},{"id":"p179950","number":"10","position":"Forward","status":"Sub","name":{"firstName":"Kirim","lastName":"Ansarifard"}},{"id":"p184483","number":"17","position":"Defender","status":"Sub","name":{"firstName":"Ahmad","lastName":"Alnameh"}},{"id":"p155079","number":"19","position":"Defender","status":"Sub","name":{"firstName":"Hashem","lastName":"Beikzadeh"}},{"id":"p165210","number":"9","position":"Forward","status":"Sub","name":{"firstName":"Alireza","lastName":"Jahanbakhsh"}},{"id":"p184497","number":"11","position":"Midfielder","status":"Sub","name":{"firstName":"Ghasem","lastName":"Haddadifar"}},{"id":"p179741","number":"18","position":"Midfielder","status":"Sub","name":{"firstName":"Bakhtiar","lastName":"Rahmani"}},{"id":"p69179","number":"22","position":"Goalkeeper","status":"Sub","name":{"firstName":"Daniel","lastName":"Davari"}},{"id":"p184502","number":"8","position":"Midfielder","status":"Sub","name":{"firstName":"Reza","lastName":"Haghighi"}}]},"shootout":[]}}